defectio/__init__.py
defectio/backoff.py
defectio/client.py
defectio/context_managers.py
defectio/errors.py
defectio/ext/commands/__init__.py
defectio/ext/commands/_types.py
defectio/ext/commands/bot.py
defectio/ext/commands/cog.py
defectio/ext/commands/context.py
defectio/ext/commands/converter.py
defectio/ext/commands/cooldowns.py
defectio/ext/commands/core.py
defectio/ext/commands/errors.py
defectio/ext/commands/flags.py
defectio/ext/commands/help.py
defectio/ext/commands/utils.py
defectio/ext/commands/view.py
defectio/ext/tasks/__init__.py
defectio/gateway.py
defectio/http.py
defectio/models/__init__.py
defectio/models/abc.py
defectio/models/apiinfo.py
defectio/models/attachment.py
defectio/models/auth.py
defectio/models/channel.py
defectio/models/colour.py
defectio/models/embed.py
defectio/models/file.py
defectio/models/member.py
defectio/models/message.py
defectio/models/mixins.py
defectio/models/permission.py
defectio/models/raw_models.py
defectio/models/server.py
defectio/models/user.py
defectio/state.py
defectio/types/__init__.py
defectio/types/embed.py
defectio/types/payloads.py
defectio/types/websocket.py
defectio/utils.py
defectio-0.2.3a0.dist-info/LICENSE
defectio-0.2.3a0.dist-info/WHEEL
defectio-0.2.3a0.dist-info/METADATA
defectio-0.2.3a0.dist-info/RECORD
