Metadata-Version: 2.1
Name: defectio
Version: 0.2.3a0
Summary: Wrapper for Revolt API
Home-page: https://github.com/Darkflame72/defectio
License: MIT
Author: Leon Bowie
Author-email: leon@bowie-co.nz
Requires-Python: >=3.9,<4.0
Classifier: Development Status :: 3 - Alpha
Classifier: Framework :: AsyncIO
Classifier: License :: OSI Approved :: MIT License
Classifier: Natural Language :: English
Classifier: Operating System :: OS Independent
Classifier: Programming Language :: Python :: 3
Classifier: Programming Language :: Python :: 3.10
Classifier: Programming Language :: Python :: 3.9
Classifier: Topic :: Software Development :: Libraries
Classifier: Topic :: Software Development :: Libraries :: Python Modules
Classifier: Topic :: Utilities
Requires-Dist: aiofiles (>=0.7,<0.9)
Requires-Dist: aiohttp (>=3.7.4,<4.0.0)
Requires-Dist: msgpack (>=1.0.2,<2.0.0)
Requires-Dist: orjson (>=3.6.3,<4.0.0)
Requires-Dist: ulid-py (>=1.1.0,<2.0.0)
Project-URL: Documentation, https://defectio.readthedocs.io
Project-URL: Repository, https://github.com/Darkflame72/defectio
